Workbook

Sheet Project Information
A1: PROJECT INFORMATION
A3: Project Name | B3: OpenCart QA Testing
A4: Application Name | B4: OpenCart
A5: Application Type | B5: Web Application
A6: Document Type | B6: QA Test Documentation
A7: Version | B7: 1
A8: Prepared By | B8: Ghanshyam Sharma
A9: Testing Approach | B9: Manual Testing
A10: Environment | B10: OpenCart Demo
A11: Browser | B11: Chrome
A12: Operating System | B12: Windows
A13: Date | B13: 46302
A15: Documentation Index
A16: Sheet | B16: Purpose
A17: Project Information | B17: Project and testing information
A18: Test Scenarios | B18: Master list of test scenarios
A19: Module sheets | B19: Test cases per module: Register, Login, Home Page, Wishlist, Shopping Cart, Checkout, Account - My Account, Account - My Order, Account - My Affiliate, Account - Newsletter, Customer Service
A20: RTM | B20: Requirement-to-test-case mapping
A21: Defects | B21: Defects identified during testing

Sheet Test-Scenario
A1: Project Name | B1: OpenCart (Front-End)
A2: Client | B2: OpenCart
A3: Created By | B3: Ghanshyam Sharma
A4: Creation Date | B4: 46219
A5: Aproval Date
A7: Test Scenario ID | B7: Module | C7: Reference | D7: Test Scenario | E7: Priority | F7: Number of Test Cases
A8: TS_01 | B8: Register | C8: FRS | D8: Verify the working of Registration functionality under my account. | E8: P0 | F8: =COUNTIF(Register!$B$6:$B$12,A8&" -*") -> 7
A9: TS_02 | B9: Login | C9: FRS | D9: Validate the working of login functionality under my account. | E9: P0 | F9: =COUNTIF(Login!$B$6:$B$18,A9&" -*") -> 6
A10: TS_03 | B10: Login | C10: FRS | D10: validate the working of logout functionality. | E10: P0 | F10: =COUNTIF(Login!$B$6:$B$18,A10&" -*") -> 2
A11: TS_04 | B11: Login | C11: FRS | D11: Validate the working of forgot password functionality. | E11: P2 | F11: =COUNTIF(Login!$B$6:$B$18,A11&" -*") -> 5
A12: TS_05 | B12: Home Page | C12: FRS | D12: Valida the Opencart logo functionality on homepage. | E12: P0 | F12: =COUNTIF('Home Page'!$B$6:$B$38,A12&" -*") -> 3
A13: TS_06 | B13: Home Page | C13: FRS | D13: Varify the the working of currency selection dropdown functionality. | E13: P1 | F13: =COUNTIF('Home Page'!$B$6:$B$38,A13&" -*") -> 4
A14: TS_07 | B14: Home Page | C14: FRS | D14: verify the working of search product functionality | E14: P1 | F14: =COUNTIF('Home Page'!$B$6:$B$38,A14&" -*") -> 4
A15: TS_08 | B15: Home Page | C15: FRS | D15: Verify the product categories functionality. | E15: P0 | F15: =COUNTIF('Home Page'!$B$6:$B$38,A15&" -*") -> 5
A16: TS_09 | B16: Home Page | C16: FRS | D16: Verify the Product Banner slider functionality on home page. | E16: P0 | F16: =COUNTIF('Home Page'!$B$6:$B$38,A16&" -*") -> 3
A17: TS_10 | B17: Home Page | C17: FRS | D17: Verify the working of Add to card functionalty from featured product section. | E17: P0 | F17: =COUNTIF('Home Page'!$B$6:$B$38,A17&" -*") -> 4
A18: TS_11 | B18: Home Page | C18: FRS | D18: Verify the working of Wishlist from featured product section. | E18: P2 | F18: =COUNTIF('Home Page'!$B$6:$B$38,A18&" -*") -> 3
A19: TS_12 | B19: Home Page | C19: FRS | D19: Verify the user can add compare from featured product section. | E19: P3 | F19: =COUNTIF('Home Page'!$B$6:$B$38,A19&" -*") -> 4
A20: TS_13 | B20: Home Page | C20: FRS | D20: Verify the working of Brand slider functionality. | E20: P3 | F20: =COUNTIF('Home Page'!$B$6:$B$38,A20&" -*") -> 3
A21: TS_14 | B21: Wishlist | C21: FRS | D21: Verify the working of wishlist functionality. | E21: p2 | F21: =COUNTIF(Wishlist!$B$6:$B$11,A21&" -*") -> 6
A22: TS_15 | B22: Shopping Cart | C22: FRS | D22: Verify the working of shopping cart functionality. | E22: P0 | F22: =COUNTIF('Shopping Cart'!$B$6:$B$13,A22&" -*") -> 8
A23: TS_16 | B23: Checkout | C23: FRS | D23: Verufy the working of checkout functionality. | E23: P0 | F23: =COUNTIF(Checkout!$B$6:$B$18,A23&" -*") -> 13
A24: TS_17 | B24: Account - My Account | C24: FRS | D24: Verify the working of My Account information functionality. | E24: P3 | F24: =COUNTIF('Account - My Account'!$B$6:$B$23,A24&" -*") -> 4
A25: TS_18 | B25: Account - My Account | C25: FRS | D25: Validate the working of change password functionality. | E25: p4 | F25: =COUNTIF('Account - My Account'!$B$6:$B$23,A25&" -*") -> 5
A26: TS_19 | B26: Account - My Account | C26: FRS | D26: Validate the working of modify your addresss book entries functionality | E26: P1 | F26: =COUNTIF('Account - My Account'!$B$6:$B$23,A26&" -*") -> 6
A27: TS_20 | B27: Account - My Account | C27: FRS | D27: Verify working of Modify your wish list functionality. | E27: P4 | F27: =COUNTIF('Account - My Account'!$B$6:$B$23,A27&" -*") -> 3
A28: TS_21 | B28: Account - My Order | C28: FRS | D28: Verify the working of view your order functionality. | E28: P1 | F28: =COUNTIF('Account - My Order'!$B$6:$B$21,A28&" -*") -> 3
A29: TS_22 | B29: Account - My Order | C29: FRS | D29: Verify the working of subscription functionality. | E29: P4 | F29: =COUNTIF('Account - My Order'!$B$6:$B$21,A29&" -*") -> 3
A30: TS_23 | B30: Account - My Order | C30: FRS | D30: Verify the working of Downloads functionality. | E30: P4 | F30: =COUNTIF('Account - My Order'!$B$6:$B$21,A30&" -*") -> 3
A31: TS_24 | B31: Account - My Order | C31: FRS | D31: Verify the working of Your reward points functionality. | E31: P1 | F31: =COUNTIF('Account - My Order'!$B$6:$B$21,A31&" -*") -> 4
A32: TS_25 | B32: Account - My Order | C32: FRS | D32: Verify the working of Your Transactions functionality. | E32: P1 | F32: =COUNTIF('Account - My Order'!$B$6:$B$21,A32&" -*") -> 3
A33: TS_26 | B33: Account - My Affiliate | C33: FRS | D33: Verify the working of Register for an affiliate account functionality. | E33: P0 | F33: =COUNTIF('Account - My Affiliate'!$B$6:$B$10,A33&" -*") -> 5
A34: TS_27 | B34: Account - Newsletter | C34: FRS | D34: Verify the working of Subscribe functionality. | E34: P2 | F34: =COUNTIF('Account - Newsletter'!$B$6:$B$11,A34&" -*") -> 3
A35: TS_28 | B35: Account - Newsletter | C35: FRS | D35: Verify the working of Unsubscribe functionality. | E35: P4 | F35: =COUNTIF('Account - Newsletter'!$B$6:$B$11,A35&" -*") -> 3
A36: TS_29 | B36: Customer Service | C36: FRS | D36: Verify the working of Contact us page functionality under footer. | E36: P2 | F36: =COUNTIF('Customer Service'!$B$6:$B$11,A36&" -*") -> 6

Sheet Register
A1: Client Name | B1: OpenCart
A2: Prepared By | B2: Ghanshyam Sharma
A3: Version Number | B3: Version 1.0 Version 2.0
A4: Module | B4: Register
A5: Test Case ID | B5: Test Scenario | C5: Test Case Title | D5: Pre-Condition | E5: Test Step | F5: Test Data | G5: Expected Result | H5: Actual Result | I5: Priority | J5: Result
A6: TC-RF-01 | B6: TS_01 - Registration Functionality | C6: Register with valid details | D6: Application is open; user is not logged in | E6: 1. Open the OpenCart demo home page 2. Click My Account > Register 3. Enter all mandatory details 4. Tick the Privacy Policy checkbox 5. Click Continue | F6: First Name: Ghanshyam Last Name: Sharma Email: qa.ghanshyam01@example.com Password: Test@1234 | G6: Account is created; "Your Account Has Been Created!" page is displayed and the user is logged in | I6: P0 | J6: Not Executed
A7: TC-RF-02 | B7: TS_01 - Registration Functionality | C7: Register with all mandatory fields blank | D7: Register page is open | E7: 1. Leave all fields empty 2. Click Continue | F7: No data | G7: Inline errors are shown for First Name, Last Name, E-Mail, Password and the Privacy Policy warning; no account is created | I7: P1 | J7: Not Executed
A8: TC-RF-03 | B8: TS_01 - Registration Functionality | C8: Register with an already registered e-mail | D8: Account from TC-RF-01 exists | E8: 1. Open the Register page 2. Enter valid details using the existing e-mail 3. Tick Privacy Policy 4. Click Continue | F8: Email: qa.ghanshyam01@example.com | G8: Warning that the e-mail address is already registered is shown; no duplicate account is created | I8: P1 | J8: Not Executed
A9: TC-RF-04 | B9: TS_01 - Registration Functionality | C9: Register with invalid e-mail format | D9: Register page is open | E9: 1. Fill valid details but enter an invalid e-mail 2. Tick Privacy Policy 3. Click Continue | F9: Email: ghanshyam@@example | G9: Error stating the e-mail address does not appear to be valid | I9: P1 | J9: Not Executed
A10: TC-RF-05 | B10: TS_01 - Registration Functionality | C10: Register with password shorter than minimum length | D10: Register page is open | E10: 1. Fill valid details with a 3-character password 2. Tick Privacy Policy 3. Click Continue | F10: Password: Ab1 | G10: Error stating the password must be between 4 and 20 characters | I10: P2 | J10: Not Executed
A11: TC-RF-06 | B11: TS_01 - Registration Functionality | C11: Register without accepting the Privacy Policy | D11: Register page is open | E11: 1. Fill all fields with valid data 2. Do NOT tick Privacy Policy 3. Click Continue | F11: Valid details from TC-RF-01 | G11: Warning that the Privacy Policy must be accepted is shown; account is not created | I11: P1 | J11: Not Executed
A12: TC-RF-07 | B12: TS_01 - Registration Functionality | C12: Register with First Name longer than 32 characters | D12: Register page is open | E12: 1. Enter a 33-character First Name with other valid data 2. Tick Privacy Policy 3. Click Continue | F12: First Name: 33 x "A" | G12: Error stating First Name must be between 1 and 32 characters | I12: P2 | J12: Not Executed

Sheet Login
A1: Client Name | B1: OpenCart
A2: Prepared By | B2: Ghanshyam Sharma
A3: Version Number | B3: Version 1.0 Version 2.0
A4: Module | B4: Login
A5: Test Case ID | B5: Test Scenario | C5: Test Case Title | D5: Pre-Condition | E5: Test Step | F5: Test Data | G5: Expected Result | H5: Actual Result | I5: Priority | J5: Result
A6: TC-LF-01 | B6: TS_02 - Login Functionality | C6: Login with valid credentials | D6: Registered account exists; user is logged out | E6: 1. Click My Account > Login 2. Enter registered e-mail and password 3. Click Login | F6: Email: qa.ghanshyam01@example.com Password: Test@1234 | G6: User is logged in and redirected to the My Account page | I6: P0 | J6: Not Executed
A7: TC-LF-02 | B7: TS_02 - Login Functionality | C7: Login with valid e-mail and wrong password | D7: Registered account exists | E7: 1. Open the Login page 2. Enter valid e-mail and an incorrect password 3. Click Login | F7: Email: qa.ghanshyam01@example.com Password: Wrong@999 | G7: Warning that e-mail/password does not match is shown; user stays on the login page | I7: P0 | J7: Not Executed
A8: TC-LF-03 | B8: TS_02 - Login Functionality | C8: Login with an unregistered e-mail | D8: Login page is open | E8: 1. Enter an e-mail that has no account 2. Enter any password 3. Click Login | F8: Email: nouser.9999@example.com Password: Test@1234 | G8: Warning that e-mail/password does not match is shown; no login | I8: P1 | J8: Not Executed
A9: TC-LF-04 | B9: TS_02 - Login Functionality | C9: Login with blank e-mail and password | D9: Login page is open | E9: 1. Leave both fields empty 2. Click Login | F9: No data | G9: Login is rejected with a warning; user is not logged in | I9: P1 | J9: Not Executed
A10: TC-LF-05 | B10: TS_02 - Login Functionality | C10: Password field is masked | D10: Login page is open | E10: 1. Type a password in the Password field | F10: Password: Test@1234 | G10: Characters are masked (shown as dots/asterisks) | I10: P2 | J10: Not Executed
A11: TC-LF-06 | B11: TS_02 - Login Functionality | C11: Account lock after repeated failed logins | D11: Use a dedicated test account (not the main one) | E11: 1. Attempt login with a wrong password repeatedly (5+ times) 2. Attempt login with the correct password | F11: Email: qa.lock01@example.com | G11: Warning that login attempts were exceeded is shown; login is blocked for the lock period | I11: P2 | J11: Not Executed
A12: TC-LO-01 | B12: TS_03 - Logout Functionality | C12: Logout from My Account | D12: User is logged in | E12: 1. Click My Account > Logout | F12: Logged-in user | G12: "Account Logout" page is shown; header menu now offers Login/Register instead of Logout | I12: P0 | J12: Not Executed
A13: TC-LO-02 | B13: TS_03 - Logout Functionality | C13: Account pages not accessible after logout | D13: User has just logged out | E13: 1. Click the browser Back button 2. Try opening the My Account page directly | F13: Logged-out session | G13: User is redirected to the Login page; account data is not displayed | I13: P0 | J13: Not Executed
A14: TC-FP-01 | B14: TS_04 - Forgot Password Functionality | C14: Open Forgotten Password page from Login | D14: Login page is open | E14: 1. Click the "Forgotten Password" link | F14: No data | G14: Forgotten Your Password page opens with an E-Mail Address field and Continue button | I14: P2 | J14: Not Executed
A15: TC-FP-02 | B15: TS_04 - Forgot Password Functionality | C15: Reset request with registered e-mail | D15: Registered account exists | E15: 1. Open Forgotten Password page 2. Enter registered e-mail 3. Click Continue | F15: Email: qa.ghanshyam01@example.com | G15: Success message that a confirmation/reset link has been e-mailed; user returns to Login page | I15: P2 | J15: Not Executed
A16: TC-FP-03 | B16: TS_04 - Forgot Password Functionality | C16: Reset request with unregistered e-mail | D16: Forgotten Password page is open | E16: 1. Enter an e-mail with no account 2. Click Continue | F16: Email: nouser.9999@example.com | G16: Warning that the e-mail address was not found is shown | I16: P2 | J16: Not Executed
A17: TC-FP-04 | B17: TS_04 - Forgot Password Functionality | C17: Reset request with blank e-mail | D17: Forgotten Password page is open | E17: 1. Leave e-mail empty 2. Click Continue | F17: No data | G17: Warning is shown; no reset e-mail is requested | I17: P3 | J17: Not Executed
A18: TC-FP-05 | B18: TS_04 - Forgot Password Functionality | C18: Back button on Forgotten Password page | D18: Forgotten Password page is open | E18: 1. Click Back | F18: No data | G18: User is returned to the Login page | I18: P3 | J18: Not Executed

Sheet Home Page
A1: Client Name | B1: OpenCart
A2: Prepared By | B2: Ghanshyam Sharma
A3: Version Number | B3: Version 1.0 Version 2.0
A4: Module | B4: Home Page
A5: Test Case ID | B5: Test Scenario | C5: Test Case Title | D5: Pre-Condition | E5: Test Step | F5: Test Data | G5: Expected Result | H5: Actual Result | I5: Priority | J5: Result
A6: TC-LG-01 | B6: TS_05 - Logo Functionality | C6: Logo is displayed correctly on home page | D6: Home page is open | E6: 1. Observe the OpenCart/store logo in the header | F6: No data | G6: Logo is visible, not distorted or broken, and aligned in the header | I6: P0 | J6: Not Executed
A7: TC-LG-02 | B7: TS_05 - Logo Functionality | C7: Click logo on the home page | D7: Home page is open | E7: 1. Click the logo | F7: No data | G7: Home page reloads; no error is shown | I7: P0 | J7: Not Executed
A8: TC-LG-03 | B8: TS_05 - Logo Functionality | C8: Click logo from an inner page | D8: User is on a product or cart page | E8: 1. Click the logo | F8: Page: Shopping Cart | G8: User is redirected to the home page | I8: P0 | J8: Not Executed
A9: TC-CU-01 | B9: TS_06 - Currency Selection Functionality | C9: Currency dropdown lists available currencies | D9: Home page is open | E9: 1. Click the Currency dropdown | F9: No data | G9: Dropdown lists the available currencies (e.g. Euro, Pound Sterling, US Dollar) | I9: P1 | J9: Not Executed
A10: TC-CU-02 | B10: TS_06 - Currency Selection Functionality | C10: Change currency updates product prices | D10: Home page is open | E10: 1. Select Euro from the dropdown 2. Observe featured product prices | F10: Currency: Euro | G10: Currency symbol changes and prices are converted on the page | I10: P1 | J10: Not Executed
A11: TC-CU-03 | B11: TS_06 - Currency Selection Functionality | C11: Selected currency persists across pages | D11: Currency changed to Euro | E11: 1. Open a category page 2. Open a product page | F11: Currency: Euro | G11: Selected currency is retained on all pages | I11: P1 | J11: Not Executed
A12: TC-CU-04 | B12: TS_06 - Currency Selection Functionality | C12: Cart and checkout totals follow selected currency | D12: Currency is Euro; cart has a product | E12: 1. Open the cart 2. Open checkout | F12: Currency: Euro | G12: Cart and checkout amounts are shown in the selected currency | I12: P2 | J12: Not Executed
A13: TC-SP-01 | B13: TS_07 - Search Product Functionality | C13: Search for an existing product | D13: Home page is open | E13: 1. Type a product name in the search box 2. Click the search icon | F13: Search: iPhone | G13: Search results page lists matching product(s) with image, name, price and Add to Cart | I13: P1 | J13: Not Executed
A14: TC-SP-02 | B14: TS_07 - Search Product Functionality | C14: Search for a non-existent product | D14: Home page is open | E14: 1. Type a non-existent keyword 2. Click the search icon | F14: Search: zzzxyz123 | G14: Message "There is no product that matches the search criteria." is displayed | I14: P1 | J14: Not Executed
A15: TC-SP-03 | B15: TS_07 - Search Product Functionality | C15: Search with empty keyword | D15: Home page is open | E15: 1. Leave the search box empty 2. Click the search icon | F15: No data | G15: No product results are listed; the page shows the search form without errors | I15: P2 | J15: Not Executed
A16: TC-SP-04 | B16: TS_07 - Search Product Functionality | C16: Open product details from search results | D16: Search results are displayed (TC-SP-01) | E16: 1. Click the product name in the results | F16: Search: iPhone | G16: Product detail page opens with the correct name, price, description and Add to Cart button | I16: P1 | J16: Not Executed
A17: TC-PC-01 | B17: TS_08 - Product Categories Functionality | C17: Category menu shows sub-categories | D17: Home page is open | E17: 1. Hover/click the Desktops menu | F17: Menu: Desktops | G17: Sub-categories (e.g. PC, Mac, Show All Desktops) are listed | I17: P0 | J17: Not Executed
... A38: TC-BR-03 | B38: TS_13 - Brand Slider Functionality | C38: Click a brand logo | D38: Home page is open | E38: 1. Click on a brand logo | F38: Brand: Apple | G38: Brand page opens listing products of that brand | I38: P3 | J38: Not Executed

Sheet Wishlist
A1: Client Name | B1: OpenCart
A2: Prepared By | B2: Ghanshyam Sharma
A3: Version Number | B3: Version 1.0 Version 2.0
A4: Module | B4: Wishlist
A5: Test Case ID | B5: Test Scenario | C5: Test Case Title | D5: Pre-Condition | E5: Test Step | F5: Test Data | G5: Expected Result | H5: Actual Result | I5: Priority | J5: Result
A6: TC-WL-01 | B6: TS_14 - Wishlist Functionality | C6: Wishlist redirects guest to login | D6: User is logged out | E6: 1. Open the Wish List page from the header | F6: Logged-out user | G6: User is redirected to the Login page | I6: P2 | J6: Not Executed
A7: TC-WL-02 | B7: TS_14 - Wishlist Functionality | C7: View an empty wishlist | D7: Logged in; wishlist is empty | E7: 1. Open My Account > Wish List | F7: No products | G7: Message that the wish list is empty is shown | I7: P2 | J7: Not Executed
A8: TC-WL-03 | B8: TS_14 - Wishlist Functionality | C8: View wishlist with products | D8: Product added to wishlist | E8: 1. Open the Wish List page | F8: Product: MacBook | G8: Product is listed with image, name, model, stock and price | I8: P2 | J8: Not Executed
A9: TC-WL-04 | B9: TS_14 - Wishlist Functionality | C9: Add product to cart from wishlist | D9: Wishlist has a product | E9: 1. Click Add to Cart on the wishlist item | F9: Product: MacBook | G9: Product is added to the cart with a success alert | I9: P2 | J9: Not Executed
A10: TC-WL-05 | B10: TS_14 - Wishlist Functionality | C10: Remove product from wishlist | D10: Wishlist has a product | E10: 1. Click Remove on the wishlist item | F10: Product: MacBook | G10: Product is removed from the wishlist | I10: P2 | J10: Not Executed
A11: TC-WL-06 | B11: TS_14 - Wishlist Functionality | C11: Wishlist persists after re-login | D11: Wishlist has a product | E11: 1. Logout 2. Login again 3. Open the Wish List | F11: Email: qa.ghanshyam01@example.com Password: Test@1234 | G11: Wishlist items are still present | I11: P3 | J11: Not Executed

Sheet Shopping Cart
A1: Client Name | B1: OpenCart
A2: Prepared By | B2: Ghanshyam Sharma
A3: Version Number | B3: Version 1.0 Version 2.0
A4: Module | B4: Shopping Cart
A5: Test Case ID | B5: Test Scenario | C5: Test Case Title | D5: Pre-Condition | E5: Test Step | F5: Test Data | G5: Expected Result | H5: Actual Result | I5: Priority | J5: Result
A6: TC-SC-01 | B6: TS_15 - Shopping Cart Functionality | C6: View the shopping cart contents | D6: Cart has at least one product | E6: 1. Click the Shopping Cart link in the header | F6: Product: MacBook | G6: Cart page lists image, name, model, quantity, unit price and total for each item | I6: P0 | J6: Not Executed
A7: TC-SC-02 | B7: TS_15 - Shopping Cart Functionality | C7: Update product quantity in cart | D7: Cart has one product | E7: 1. Change quantity to 3 2. Click the Update button | F7: Qty: 3 | G7: Quantity updates and line total / cart totals recalculate correctly | I7: P0 | J7: Not Executed
A8: TC-SC-03 | B8: TS_15 - Shopping Cart Functionality | C8: Remove a product from cart | D8: Cart has one product | E8: 1. Click the Remove button on the product | F8: Product: MacBook | G8: Product is removed; "Your shopping cart is empty!" is shown when it was the last item | I8: P0 | J8: Not Executed
A9: TC-SC-04 | B9: TS_15 - Shopping Cart Functionality | C9: Update quantity to 0 | D9: Cart has one product | E9: 1. Set quantity to 0 2. Click Update | F9: Qty: 0 | G9: Product is removed from the cart | I9: P2 | J9: Not Executed
A10: TC-SC-05 | B10: TS_15 - Shopping Cart Functionality | C10: Proceed to checkout from cart | D10: Cart has at least one product | E10: 1. Click the Checkout button on the cart page | F10: Product: MacBook | G10: Checkout page opens with the cart contents | I10: P0 | J10: Not Executed
A11: TC-SC-06 | B11: TS_15 - Shopping Cart Functionality | C11: Cart persists after logout and login | D11: Logged-in user has items in cart | E11: 1. Logout 2. Login again with the same account 3. Open the cart | F11: Email: qa.ghanshyam01@example.com Password: Test@1234 | G11: Previously added items are still present in the cart | I11: P2 | J11: Not Executed
A12: TC-SC-07 | B12: TS_15 - Shopping Cart Functionality | C12: Checkout with an empty cart | D12: Cart is empty | E12: 1. Open the checkout URL directly | F12: Empty cart | G12: User is redirected to the shopping cart page; checkout does not proceed | I12: P1 | J12: Not Executed
A13: TC-SC-08 | B13: TS_15 - Shopping Cart Functionality | C13: Apply an invalid coupon code | D13: Cart has at least one product | E13: 1. Expand "Use Coupon Code" 2. Enter an invalid coupon 3. Click Apply Coupon | F13: Coupon: INVALID123 | G13: Warning that the coupon is invalid, expired or reached its limit is shown; totals unchanged | I13: P2 | J13: Not Executed

Sheet Checkout
A1: Client Name | B1: OpenCart
A2: Prepared By | B2: Ghanshyam Sharma
A3: Version Number | B3: Version 1.0 Version 2.0
A4: Module | B4: Checkout
A5: Test Case ID | B5: Test Scenario | C5: Test Case Title | D5: Pre-Condition | E5: Test Step | F5: Test Data | G5: Expected Result | H5: Actual Result | I5: Priority | J5: Result
A6: TC-CO-01 | B6: TS_16 - Checkout Functionality | C6: Checkout page loads for logged-in user | D6: User is logged in; cart has a product | E6: 1. Open Shopping Cart > Checkout | F6: Product: MacBook | G6: Checkout page shows personal details, shipping address, shipping method, payment method and order summary | I6: P0 | J6: Not Executed
A7: TC-CO-02 | B7: TS_16 - Checkout Functionality | C7: Checkout with mandatory address fields blank | D7: Logged in; cart has a product; new address form is open | E7: 1. Leave address fields empty 2. Continue / Confirm Order | F7: No data | G7: Validation errors are displayed for the mandatory address fields; order is not placed | I7: P1 | J7: Not Executed
A8: TC-CO-03 | B8: TS_16 - Checkout Functionality | C8: Enter a valid new shipping address | D8: Logged in; cart has a product | E8: 1. Choose to enter a new address 2. Fill all mandatory fields 3. Save/continue | F8: First Name: Ghanshyam Last Name: Sharma Address 1: 12 MG Road City: Patna Post Code: 800001 Country: India Region/State: Bihar | G8: Address is accepted and shown as the shipping address | I8: P0 | J8: Not Executed
A9: TC-CO-04 | B9: TS_16 - Checkout Functionality | C9: Select shipping method | D9: Shipping address is set | E9: 1. Select the Flat Shipping Rate method 2. Continue | F9: Shipping: Flat Shipping Rate | G9: Shipping method is saved and the shipping cost is added to the order totals | I9: P0 | J9: Not Executed
A10: TC-CO-05 | B10: TS_16 - Checkout Functionality | C10: Select payment method | D10: Shipping method is selected | E10: 1. Select Cash On Delivery as the payment method 2. Continue | F10: Payment: Cash On Delivery | G10: Payment method is saved and shown in the order summary | I10: P0 | J10: Not Executed
A11: TC-CO-06 | B11: TS_16 - Checkout Functionality | C11: Confirm order without selecting a payment method | D11: Address and shipping method are set | E11: 1. Do not select a payment method 2. Click Confirm Order | F11: No payment method | G11: Warning that a payment method is required is shown; order is not placed | I11: P0 | J11: Not Executed
A12: TC-CO-07 | B12: TS_16 - Checkout Functionality | C12: Confirm order without selecting a shipping method | D12: Address is set | E12: 1. Do not select a shipping method 2. Click Confirm Order | F12: No shipping method | G12: Warning that a shipping method is required is shown; order is not placed | I12: P0 | J12: Not Executed
A13: TC-CO-08 | B13: TS_16 - Checkout Functionality | C13: Verify order total calculation | D13: Cart has MacBook (qty 1); Flat Shipping Rate selected | E13: 1. Review Sub-Total, Flat Shipping Rate, taxes and Total in the order summary | F13: Product: MacBook Shipping: Flat Shipping Rate | G13: Total = Sub-Total + Shipping + Taxes (calculated correctly for the displayed currency) | I13: P0 | J13: Not Executed
A14: TC-CO-09 | B14: TS_16 - Checkout Functionality | C14: Add a comment to the order | D14: Checkout page is open | E14: 1. Enter text in the order comments box 2. Complete the order | F14: Comment: Please deliver after 5 PM | G14: Order is placed with the comment retained | I14: P3 | J14: Not Executed
A15: TC-CO-10 | B15: TS_16 - Checkout Functionality | C15: End-to-end: Login > Search > Cart > Checkout > Payment > Order Confirmation | D15: Registered account exists; user is logged out | E15: 1. Login with valid credentials 2. Search for a product and open it 3. Add it to the cart 4. Open Shopping Cart and verify items and totals 5. Click Checkout 6. Select/enter shipping address 7. Select Flat Shipping Rate 8. Select Cash On Delivery 9. Review the order summary and click Confirm Order | F15: Email: qa.ghanshyam01@example.com Password: Test@1234 Product: iPhone Qty: 1 Address: 12 MG Road, Patna, 800001, India, Bihar Shipping: Flat Shipping Rate Payment: Cash On Delivery | G15: Order is placed and the "Your order has been placed!" confirmation page is displayed | I15: P0 | J15: Not Executed
A16: TC-CO-11 | B16: TS_16 - Checkout Functionality | C16: Verify order confirmation page | D16: Order placed in TC-CO-10 | E16: 1. Review the confirmation page 2. Click Continue | F16: Placed order | G16: Page shows the success message and links to account, order history and downloads; Continue returns to the home page | I16: P0 | J16: Not Executed
A17: TC-CO-12 | B17: TS_16 - Checkout Functionality | C17: Cart is emptied after a successful order | D17: Order placed in TC-CO-10 | E17: 1. Check the header cart 2. Open the Shopping Cart page | F17: Placed order | G17: Cart shows 0 items and "Your shopping cart is empty!" message | I17: P0 | J17: Not Executed
A18: TC-CO-13 | B18: TS_16 - Checkout Functionality | C18: Guest checkout with valid details | D18: User is logged out; cart has a product | E18: 1. Open Checkout 2. Choose Guest Checkout and enter personal and address details 3. Select Flat Shipping Rate and Cash On Delivery 4. Click Confirm Order | F18: First Name: Guest Last Name: Tester Email: guest.tester01@example.com First Name: Ghanshyam Last Name: Sharma Address 1: 12 MG Road City: Patna Post Code: 800001 Country: India Region/State: Bihar | G18: Order is placed without creating an account; confirmation page is displayed | I18: P1 | J18: Not Executed

Sheet Account - My Account
A1: Client Name | B1: OpenCart
A2: Prepared By | B2: Ghanshyam Sharma
A3: Version Number | B3: Version 1.0 Version 2.0
A4: Module | B4: Account - My Account
A5: Test Case ID | B5: Test Scenario | C5: Test Case Title | D5: Pre-Condition | E5: Test Step | F5: Test Data | G5: Expected Result | H5: Actual Result | I5: Priority | J5: Result
A6: TC-MA-01 | B6: TS_17 - My Account Information | C6: View account information | D6: User is logged in | E6: 1. Click My Account > Edit your account information | F6: No data | G6: Form opens with first name, last name, e-mail and telephone pre-filled | I6: P3 | J6: Not Executed
A7: TC-MA-02 | B7: TS_17 - My Account Information | C7: Update account information with valid data | D7: Account information page is open | E7: 1. Change the First Name 2. Click Continue | F7: First Name: Ghanshyam K | G7: Success message that the account was updated; new name is saved | I7: P3 | J7: Not Executed
A8: TC-MA-03 | B8: TS_17 - My Account Information | C8: Update with mandatory fields blank | D8: Account information page is open | E8: 1. Clear First Name, Last Name and E-Mail 2. Click Continue | F8: Blank values | G8: Validation errors are shown; no changes saved | I8: P3 | J8: Not Executed
A9: TC-MA-04 | B9: TS_17 - My Account Information | C9: Update with invalid e-mail format | D9: Account information page is open | E9: 1. Enter an invalid e-mail 2. Click Continue | F9: Email: qa@@example | G9: E-mail validation error is shown | I9: P3 | J9: Not Executed
A10: TC-CP-01 | B10: TS_18 - Change Password | C10: Change password with valid data | D10: User is logged in | E10: 1. Open My Account > Change your password 2. Enter new password and confirmation 3. Click Continue | F10: New Password: Test@5678 Confirm: Test@5678 | G10: Success message that the password has been updated | I10: P4 | J10: Not Executed
A11: TC-CP-02 | B11: TS_18 - Change Password | C11: Password and confirmation mismatch | D11: Change Password page is open | E11: 1. Enter different values in Password and Confirm 2. Click Continue | F11: Password: Test@5678 Confirm: Test@0000 | G11: Error that password confirmation does not match | I11: P4 | J11: Not Executed
A12: TC-CP-03 | B12: TS_18 - Change Password | C12: Password shorter than minimum length | D12: Change Password page is open | E12: 1. Enter a 3-character password in both fields 2. Click Continue | F12: Password: Ab1 | G12: Error that the password must be between 4 and 20 characters | I12: P4 | J12: Not Executed
A13: TC-CP-04 | B13: TS_18 - Change Password | C13: Blank password fields | D13: Change Password page is open | E13: 1. Leave both fields empty 2. Click Continue | F13: No data | G13: Validation error is shown; password is not changed | I13: P4 | J13: Not Executed
A14: TC-CP-05 | B14: TS_18 - Change Password | C14: Login with the new password after change | D14: Password changed in TC-CP-01 | E14: 1. Logout 2. Login with the old password 3. Login with the new password | F14: Old: Test@1234 New: Test@5678 | G14: Old password is rejected; new password logs in successfully | I14: P4 | J14: Not Executed
A15: TC-AB-01 | B15: TS_19 - Address Book | C15: Add a new address with valid data | D15: User is logged in | E15: 1. Open My Account > Modify your address book 2. Click New Address 3. Fill mandatory fields 4. Click Continue | F15: First Name: Ghanshyam Last Name: Sharma Address 1: 12 MG Road City: Patna Post Code: 800001 Country: India Region/State: Bihar | G15: Success message; new address appears in the address book | I15: P1 | J15: Not Executed
A16: TC-AB-02 | B16: TS_19 - Address Book | C16: Add address with mandatory fields blank | D16: New Address form is open | E16: 1. Leave fields empty 2. Click Continue | F16: No data | G16: Validation errors for mandatory fields; address is not saved | I16: P1 | J16: Not Executed
A17: TC-AB-03 | B17: TS_19 - Address Book | C17: Edit an existing address | D17: Address exists | E17: 1. Click Edit on an address 2. Change the City 3. Click Continue | F17: City: Gaya | G17: Success message; updated city is shown in the address book | I17: P1 | J17: Not Executed
... A23: TC-MW-03 | B23: TS_20 - Modify Wish List | C23: Add item to cart from the modified wishlist | D23: Wishlist has a product | E23: 1. Click Add to Cart on a product | F23: Product: MacBook | G23: Product is added to the cart | I23: P4 | J23: Not Executed

Sheet Account - My Order
A1: Client Name | B1: OpenCart
A2: Prepared By | B2: Ghanshyam Sharma
A3: Version Number | B3: Version 1.0 Version 2.0
A4: Module | B4: Account - My Order
A5: Test Case ID | B5: Test Scenario | C5: Test Case Title | D5: Pre-Condition | E5: Test Step | F5: Test Data | G5: Expected Result | H5: Actual Result | I5: Priority | J5: Result
A6: TC-MO-01 | B6: TS_21 - View Your Order | C6: Placed order appears in order history | D6: Order placed in TC-CO-10; user is logged in | E6: 1. Click My Account > Order History | F6: Placed order | G6: The new order is listed with an Order ID, date, product count, total and status (e.g. Pending) | I6: P1 | J6: Not Executed
A7: TC-MO-02 | B7: TS_21 - View Your Order | C7: View order details | D7: Order exists in Order History | E7: 1. Click the View icon for the order | F7: Placed order | G7: Details match the placed order: products, quantity, totals, address, shipping and payment methods | I7: P1 | J7: Not Executed
A8: TC-MO-03 | B8: TS_21 - View Your Order | C8: Reorder from order history | D8: Order exists in Order History | E8: 1. Click the Reorder icon for the order 2. Open the cart | F8: Placed order | G8: Products from the earlier order are added to the cart | I8: P2 | J8: Not Executed
A9: TC-SB-01 | B9: TS_22 - Subscription | C9: Open Subscription page | D9: User is logged in | E9: 1. Click My Account > Subscriptions | F9: No data | G9: Subscriptions page opens without errors | I9: P4 | J9: Not Executed
A10: TC-SB-02 | B10: TS_22 - Subscription | C10: Subscription page with no subscriptions | D10: User has no subscriptions | E10: 1. Open the Subscriptions page | F10: No subscriptions | G10: Empty-state message is displayed | I10: P4 | J10: Not Executed
A11: TC-SB-03 | B11: TS_22 - Subscription | C11: Continue button returns to account | D11: Subscriptions page is open | E11: 1. Click Continue | F11: No data | G11: User is returned to My Account page | I11: P4 | J11: Not Executed
A12: TC-DL-01 | B12: TS_23 - Downloads | C12: Open Downloads page | D12: User is logged in | E12: 1. Click My Account > Downloads | F12: No data | G12: Downloads page opens without errors | I12: P4 | J12: Not Executed
A13: TC-DL-02 | B13: TS_23 - Downloads | C13: Downloads with no downloadable orders | D13: User has no downloadable products ordered | E13: 1. Open the Downloads page | F13: No downloads | G13: Message that there are no previous downloadable orders is shown | I13: P4 | J13: Not Executed
A14: TC-DL-03 | B14: TS_23 - Downloads | C14: Download a purchased file | D14: A downloadable product was ordered and order is Complete | E14: 1. Open the Downloads page 2. Click the download icon | F14: Downloadable product (if available on demo) | G14: File downloads successfully | I14: P4 | J14: Not Executed
A15: TC-RP-01 | B15: TS_24 - Your Reward Points | C15: Open Reward Points page | D15: User is logged in | E15: 1. Click My Account > Your Reward Points | F15: No data | G15: Reward Points page opens with the total points | I15: P1 | J15: Not Executed
A16: TC-RP-02 | B16: TS_24 - Your Reward Points | C16: Reward Points with no history | D16: User has no reward points | E16: 1. Open the Reward Points page | F16: No points | G16: Message that there are no reward points is shown; total is 0 | I16: P1 | J16: Not Executed
A17: TC-RP-03 | B17: TS_24 - Your Reward Points | C17: Reward points history columns | D17: User has reward points | E17: 1. Open the Reward Points page | F17: Account with points | G17: Date added, description and points are listed correctly | I17: P2 | J17: Not Executed
... A21: TC-TR-03 | B21: TS_25 - Your Transactions | C21: Continue button returns to account | D21: Transactions page is open | E21: 1. Click Continue | F21: No data | G21: User is returned to My Account page | I21: P3 | J21: Not Executed

Sheet Account - My Affiliate
A1: Client Name | B1: OpenCart
A2: Prepared By | B2: Ghanshyam Sharma
A3: Version Number | B3: Version 1.0 Version 2.0
A4: Module | B4: Account - My Affiliate
A5: Test Case ID | B5: Test Scenario | C5: Test Case Title | D5: Pre-Condition | E5: Test Step | F5: Test Data | G5: Expected Result | H5: Actual Result | I5: Priority | J5: Result
A6: TC-AF-01 | B6: TS_26 - Register for Affiliate Account | C6: Open affiliate registration page | D6: User is logged in | E6: 1. Click My Account > Register for an affiliate account | F6: No data | G6: Affiliate registration form opens with payment method fields and terms checkbox | I6: P0 | J6: Not Executed
A7: TC-AF-02 | B7: TS_26 - Register for Affiliate Account | C7: Register affiliate with valid data | D7: Affiliate form is open | E7: 1. Fill company and payee details 2. Tick the affiliate agreement 3. Click Continue | F7: Company: QA Labs Website: https://example.com Payment: Cheque Payee: Ghanshyam Sharma | G7: Success message; affiliate account is created / pending approval | I7: P0 | J7: Not Executed
A8: TC-AF-03 | B8: TS_26 - Register for Affiliate Account | C8: Affiliate registration with mandatory fields blank | D8: Affiliate form is open | E8: 1. Leave payee/payment fields empty 2. Tick the agreement 3. Click Continue | F8: No data | G8: Validation errors are shown; affiliate account is not created | I8: P1 | J8: Not Executed
A9: TC-AF-04 | B9: TS_26 - Register for Affiliate Account | C9: Affiliate registration without accepting agreement | D9: Affiliate form is open | E9: 1. Fill valid details 2. Do NOT tick the agreement 3. Click Continue | F9: Valid details from TC-AF-02 | G9: Warning that the affiliate agreement must be accepted is shown | I9: P1 | J9: Not Executed
A10: TC-AF-05 | B10: TS_26 - Register for Affiliate Account | C10: Affiliate details can be edited after registration | D10: Affiliate account exists | E10: 1. Open My Account > Edit your affiliate information 2. Update the company name 3. Click Continue | F10: Company: QA Labs Pvt | G10: Success message; updated details are saved | I10: P2 | J10: Not Executed

Sheet Account - Newsletter
A1: Client Name | B1: OpenCart
A2: Prepared By | B2: Ghanshyam Sharma
A3: Version Number | B3: Version 1.0 Version 2.0
A4: Module | B4: Account - Newsletter
A5: Test Case ID | B5: Test Scenario | C5: Test Case Title | D5: Pre-Condition | E5: Test Step | F5: Test Data | G5: Expected Result | H5: Actual Result | I5: Priority | J5: Result
A6: TC-NS-01 | B6: TS_27 - Subscribe | C6: Subscribe to newsletter | D6: Logged in; currently unsubscribed | E6: 1. Open My Account > Subscribe / unsubscribe to newsletter 2. Select Yes 3. Click Continue | F6: Subscribe: Yes | G6: Success message that the newsletter subscription was updated | I6: P2 | J6: Not Executed
A7: TC-NS-02 | B7: TS_27 - Subscribe | C7: Subscription status is retained | D7: Subscribed in TC-NS-01 | E7: 1. Logout and login 2. Open the Newsletter page | F7: Subscribe: Yes | G7: Yes is pre-selected | I7: P2 | J7: Not Executed
A8: TC-NS-03 | B8: TS_27 - Subscribe | C8: Back button on Newsletter page | D8: Newsletter page is open | E8: 1. Click Back | F8: No data | G8: User is returned to My Account page | I8: P3 | J8: Not Executed
A9: TC-NU-01 | B9: TS_28 - Unsubscribe | C9: Unsubscribe from newsletter | D9: Logged in; currently subscribed | E9: 1. Open the Newsletter page 2. Select No 3. Click Continue | F9: Subscribe: No | G9: Success message that the subscription was updated | I9: P4 | J9: Not Executed
A10: TC-NU-02 | B10: TS_28 - Unsubscribe | C10: Unsubscribed status is retained | D10: Unsubscribed in TC-NU-01 | E10: 1. Logout and login 2. Open the Newsletter page | F10: Subscribe: No | G10: No is pre-selected | I10: P4 | J10: Not Executed
A11: TC-NU-03 | B11: TS_28 - Unsubscribe | C11: Unsubscribe when already unsubscribed | D11: Logged in; already unsubscribed | E11: 1. Select No 2. Click Continue | F11: Subscribe: No | G11: Page saves without error and status remains unsubscribed | I11: P4 | J11: Not Executed

Sheet Customer Service
A1: Client Name | B1: OpenCart
A2: Prepared By | B2: Ghanshyam Sharma
A3: Version Number | B3: Version 1.0 Version 2.0
A4: Module | B4: Customer Service
A5: Test Case ID | B5: Test Scenario | C5: Test Case Title | D5: Pre-Condition | E5: Test Step | F5: Test Data | G5: Expected Result | H5: Actual Result | I5: Priority | J5: Result
A6: TC-CS-01 | B6: TS_29 - Contact Us | C6: Open Contact Us from footer | D6: Home page is open | E6: 1. Scroll to the footer 2. Click Contact Us | F6: No data | G6: Contact Us page opens showing store details and the enquiry form | I6: P2 | J6: Not Executed
A7: TC-CS-02 | B7: TS_29 - Contact Us | C7: Submit enquiry with valid data | D7: Contact Us page is open | E7: 1. Enter name, e-mail and enquiry 2. Click Submit | F7: Name: Ghanshyam Sharma Email: qa.ghanshyam01@example.com Enquiry: Please share the delivery timelines for Patna. | G7: Success message that the enquiry was sent to the store owner | I7: P2 | J7: Not Executed
A8: TC-CS-03 | B8: TS_29 - Contact Us | C8: Submit with all fields blank | D8: Contact Us page is open | E8: 1. Leave all fields empty 2. Click Submit | F8: No data | G8: Validation errors for name, e-mail and enquiry | I8: P2 | J8: Not Executed
A9: TC-CS-04 | B9: TS_29 - Contact Us | C9: Submit with invalid e-mail | D9: Contact Us page is open | E9: 1. Enter an invalid e-mail with other valid data 2. Click Submit | F9: Email: abc@@mail | G9: E-mail validation error is shown | I9: P2 | J9: Not Executed
A10: TC-CS-05 | B10: TS_29 - Contact Us | C10: Enquiry shorter than minimum length | D10: Contact Us page is open | E10: 1. Enter a very short enquiry 2. Click Submit | F10: Enquiry: Hi | G10: Error that enquiry must be between 10 and 3000 characters | I10: P3 | J10: Not Executed
A11: TC-CS-06 | B11: TS_29 - Contact Us | C11: Name shorter than minimum length | D11: Contact Us page is open | E11: 1. Enter a 2-character name 2. Click Submit | F11: Name: Ab | G11: Error that name must be between 3 and 32 characters | I11: P3 | J11: Not Executed
